MANIFEST.in
README.md
requirements.txt
setup.py
version.py
bin/bucket
bucket.egg-info/PKG-INFO
bucket.egg-info/SOURCES.txt
bucket.egg-info/dependency_links.txt
bucket.egg-info/requires.txt
bucket.egg-info/top_level.txt
libbucket/__init__.py
libbucket/api.py
libbucket/cli.py
libbucket/exceptions.py
libbucket/lurl.py
libbucket/version.py