Metadata-Version: 1.0
Name: bucket
Version: 0.20181025
Summary: Bitbucket from command line
Home-page: https://bitbucket.org/DavidVilla/bucket
Author: David Villa Alises
Author-email: David.Villa@gmail.com
License: GPL v2 or later
Platform: UNKNOWN
